plain/passwords/CHANGELOG.md
plain/passwords/README.md
plain/passwords/__init__.py
plain/passwords/common-passwords.txt.gz
plain/passwords/core.py
plain/passwords/default_settings.py
plain/passwords/forms.py
plain/passwords/hashers.py
plain/passwords/models.py
plain/passwords/types.py
plain/passwords/types.pyi
plain/passwords/utils.py
plain/passwords/validators.py
plain/passwords/views.py
plain/passwords/templates/email/password_reset.html
plain/passwords/templates/email/password_reset.subject.txt
plain_passwords-0.19.1.dist-info/METADATA
plain_passwords-0.19.1.dist-info/WHEEL
plain_passwords-0.19.1.dist-info/licenses/LICENSE
plain_passwords-0.19.1.dist-info/RECORD
