Metadata-Version: 2.4
Name: plain.passwords
Version: 0.19.1
Summary: Password authentication for Plain.
Author-email: Dave Gaeddert <dave.gaeddert@dropseed.dev>
License-Expression: BSD-3-Clause
License-File: LICENSE
Requires-Python: >=3.13
Requires-Dist: plain<1.0.0
